{
  "Tags": [
    "collaboration tools",
    "projects & issues",
    "Release"
  ],
  "Link": "https://github.blog/changelog/2025-09-11-a-rest-api-for-github-projects-sub-issues-improvements-and-more",
  "Title": "A REST API for GitHub Projects, sub-issues improvements, and more",
  "FeedUrl": "https://github.blog/changelog/feed/",
  "Description": "You can now use the REST API to understand and manage information about your projects, and take advantage of sub-issue improvements that make it even easier to break down your…\n\nThe post [A REST API for GitHub Projects, sub-issues improvements, and more](https://github.blog/changelog/2025-09-11-a-rest-api-for-github-projects-sub-issues-improvements-and-more) appeared first on [The GitHub Blog](https://github.blog).",
  "FeedLevelAuthor": "Archive: 2025 - GitHub Changelog",
  "Author": "Allison",
  "EnhancedContent": "You can now use the REST API to understand and manage information about your projects, and take advantage of sub-issue improvements that make it even easier to break down your work.\n\n## ⚙ REST API for GitHub Projects\n\nUsing the REST API, you can:\n\n- List projects and get information about a specific project, its fields, and its items.\n- Add and delete issues and pull requests from a project.\n- Update field values for project items.\n\nCheck out [our documentation on the Projects REST API](https://docs.github.com/rest/projects) for more details.\n\n## ✨ Sub-issue improvements\n\n- Sub-issues now **inherit the Project and Milestone** of their parent issue by default.\n- Sub-issues now support **cross-organization** issues, allowing a sub-issue to belong to a different organization than its parent.\n- The REST API now includes an endpoint to **fetch the parent issue** for a given issue. See the [API documentation](https://docs.github.com/en/rest/issues/sub-issues?apiVersion=2022-11-28#get-parent-issue) for details.\n\n## 📜 Sticky sidebar on issues\n\nWe’ve introduced a sticky sidebar that stays visible as you scroll your issues, making it easier to view and update assignees, labels, types, milestones, and projects while reading long comment threads. No need to scroll back to the top!\n\n## 🏷️ GitHub for Microsoft Teams app renamed\n\nThe [GitHub for Microsoft Teams app](https://appsource.microsoft.com/en-us/product/office/wa200002077?tab=overview) has been renamed to GitHub Notifications. This update reflects the app’s focus on delivering GitHub notifications directly into Teams.\n\nPreviously, you could mention the app in Teams using `@GitHub` . You should now use `@GitHub Notifications` .\n\nAll existing functionality remains the same, and no user action is required.\n\n## ✍️ Tell us what you think!\n\nJoin the conversation within [GitHub Community](https://github.com/orgs/community/discussions/categories/projects-and-issues), or select **Give feedback** from the projects **…** menu to share your feedback!\n\nSee how to use GitHub for project planning with [GitHub Issues and Projects](https://github.com/features/issues), check out what’s on the [roadmap](https://github.com/orgs/github/projects/4247/views/1), and learn more in [our GitHub Issues documentation](https://docs.github.com/issues).",
  "PubDate": "2025-09-11T18:42:31+00:00",
  "FeedName": "The GitHub Blog",
  "ProcessedDate": "2025-09-12 11:12:04",
  "OutputDir": "_news"
}
