{
  "FeedName": "Microsoft Developer YouTube",
  "EnhancedContent": null,
  "Link": "https://www.youtube.com/watch?v=X-Dh9R3Opn8",
  "FeedLevelAuthor": "Microsoft Developer",
  "Author": "Microsoft Developer",
  "Title": "Using Agentic Protocols (MCP, A2A, and NLWeb)",
  "ProcessedDate": "2025-08-27 16:14:52",
  "OutputDir": "_videos",
  "Description": "Find the full \"AI Agents for Beginners\" Course and code samples here ➡️ aka.ms/ai-agents-beginners Join the Discord to get your questions answered here ➡️ aka.ms/ai-agents/discord\n\nIn this lesson (11) we explore 3 different Agentic Protocols - Model Context Protocol (MCP), Agent to Agent (A2A), and NLWeb. We then look at code samples to see how to use them with our AI Agents.\n\n⏱️ Chapters 00:00 - Introduction 00:56 - MCP - Concepts 02:45 - MCP - Code 07:22 - A2A - Concepts 08:43 - A2A - Code 13:20 - NLWEb - Concepts\n\nCheck in with Korey here: https://www.linkedin.com/in/koreyspace/ https://github.com/koreyspace https://x.com/koreyspace",
  "Tags": [
    "Azure",
    "Cloud Computing",
    "Dev",
    "Development",
    "Microsoft",
    "Tech",
    "Technology"
  ],
  "FeedUrl": "https://www.youtube.com/feeds/videos.xml?channel_id=UCsMica-v34Irf9KVTh6xx-g",
  "PubDate": "2025-08-27T16:00:56+00:00"
}
