{
  "EnhancedContent": null,
  "FeedLevelAuthor": "John Savill's Technical Training",
  "Tags": [
    "azure",
    "azure cloud",
    "cloud",
    "expressroute",
    "gateway",
    "microsoft",
    "microsoft azure",
    "networking"
  ],
  "PubDate": "2026-02-26T08:36:23+00:00",
  "Link": "https://www.youtube.com/shorts/uLsM-wl6xUA",
  "Author": "John Savill's Technical Training",
  "OutputDir": "_videos",
  "Title": "ExpressRoute Scalable Gateway #azure #networking",
  "Description": "Quick look at the new scalable ExpressRoute Gateway SKU.",
  "FeedName": "John Savill's Technical Training",
  "FeedUrl": "https://www.youtube.com/feeds/videos.xml?channel_id=UCpIn7ox7j7bH_OFj7tYouOQ",
  "ProcessedDate": "2026-02-26 09:15:03"
}
