{
  "PubDate": "2025-09-24T18:24:13+00:00",
  "Tags": [
    "Drones",
    "GitHub",
    "OpenSource"
  ],
  "OutputDir": "_videos",
  "Author": "GitHub",
  "Link": "https://www.youtube.com/watch?v=EHccwVnNK4c",
  "EnhancedContent": null,
  "Description": "In one of Africa's largest refugee camps, an incredible tech-for-good story is unfolding. See how UNHCR and the local community in Kakuma are using community-flown drones, AI, and open source tools on GitHub to create the first-ever detailed maps of their home. This vital data is the first step in building a sustainable future.\n\nLearn more about this incredible tech-for-good initiative. 👇 https://github.blog/open-source/social-impact/using-ai-to-map-hope-for-refugees-with-unhcr-the-un-refugee-agency/\n\n#Drones #GitHub #OpenSource\n\nStay up-to-date on all things GitHub by connecting with us:\n\nYouTube: https://gh.io/subgithub Blog: https://github.blog X: https://twitter.com/github LinkedIn: https://linkedin.com/company/github Insider newsletter: https://resources.github.com/newsletter/ Instagram: https://www.instagram.com/github TikTok: https://www.tiktok.com/@github\n\nAbout GitHub It’s where over 100 million developers create, share, and ship the best code possible. It’s a place for anyone, from anywhere, to build anything—it’s where the world builds software. https://github.com",
  "FeedLevelAuthor": "GitHub",
  "FeedUrl": "https://www.youtube.com/feeds/videos.xml?channel_id=UC7c3Kb6jYCRj4JOHHZTxKsQ",
  "Title": "How drones and open source are building maps for refugees",
  "ProcessedDate": "2025-09-24 19:10:11",
  "FeedName": "GitHub YouTube"
}
