{
  "Tags": [],
  "Author": "Microsoft Fabric Blog",
  "OutputDir": "_news",
  "FeedName": "Microsoft Fabric Blog",
  "Link": "https://blog.fabric.microsoft.com/en-US/blog/on-premises-data-gateway-auto-update-admin-triggered-generally-available/",
  "FeedLevelAuthor": "Microsoft Fabric Blog",
  "PubDate": "2026-03-18T05:46:50+00:00",
  "Title": "On-premises data gateway auto-update (admin triggered) (Generally Available)",
  "Description": "If you haven’t already, check out Arun Ulag’s hero blog “FabCon and SQLCon 2026: Unifying databases and Fabric on a single, complete platform” for a complete look at all of our FabCon and SQLCon announcements across both Fabric and our database offerings. The on-premises data gateway auto-update (admin triggered), this capability gives administrators greater control …\n\n[Continue reading “On-premises data gateway auto-update (admin triggered) (Generally Available)”](https://blog.fabric.microsoft.com/en-us/blog/on-premises-data-gateway-auto-update-admin-triggered-generally-available/)",
  "EnhancedContent": "*If you haven’t already, check out Arun Ulag’s hero blog “*[*FabCon and SQLCon 2026: Unifying databases and Fabric on a single, complete platform*](https://aka.ms/FabCon-SQLCon-2026-news)*” for a complete look at all of our FabCon and SQLCon announcements across both Fabric and our database offerings.*\n\nThe **on-premises data gateway auto-update (admin triggered),** this capability gives administrators greater control over how and when gateway updates are applied, making it easier to align with organizational maintenance windows, change management processes, and compliance requirements.\n\nWith auto-update (admin triggered), gateway administrators can trigger upgrades on demand. This helps organizations adopt new features, performance improvements, and security patches at a time that best fits their operational needs.\n\n## What’s new with auto-update (admin triggered)\n\nWith this release of auto-update (admin triggered), administrators can:\n\n- **Trigger gateway updates on demand** instead of installing/uninstalling in local machines.\n- **Control update timing** to match internal maintenance windows and policies.\n- **Reduce operational risk** by planning and validating updates before deployment.\n- **Apply updates programmatically** using PowerShell or scripts for automation scenarios.\n- **Standardize update processes** across multiple servers or clusters.\n\nAuto-update (admin triggered) is especially useful for enterprises that require staged deployment, validation in test environments, or strict change control procedures.\n\n### Baseline version requirement\n\nThe **November 2025 release** serves as the baseline version for the auto-update (admin triggered) feature. Gateways must be updated to this version (or later) to use auto-update (admin triggered) capabilities.\n\n## Getting started\n\n1. **Update to the baseline version** – Ensure your gateway is running the November 2025 release or a newer version.\n2. **Check for available updates in the gateway UI –** Open the on-premises data gateway UI. When a newer version is available, you will see an update indicator that shows version availability details.\n\n![Screenshot of the gateway manual update from the UI.](//dataplatformblogwebfd-d3h9cbawf0h8ecgf.b01.azurefd.net/wp-content/uploads/2026/03/screenshot-of-the-gateway-manual-update-from-the-u.png)\n\n*Figure: Administrators can trigger on-premises data gateway auto-updates to quickly apply the latest improvements, security fixes, and reliability enhancements.*\n\n1. **Trigger the update manually** – Select the update icon to start the manual upgrade process when you are ready.\n2. **Use PowerShell for programmatic updates (optional)** – You can also initiate updates through PowerShell or automation scripts.\n\n**Example**:\n\nUpdate-DataGatewayClusterMember -GatewayClusterId DC8F2C49-5731-4B27-966B-3DB5094C2E77\n\nThis enables centralized and repeatable update workflows across environments.\n\n## Looking ahead\n\nAuto-update (admin triggered) is a key step toward more flexible and enterprise-ready gateway lifecycle management. We will continue investing in update and maintenance experiences, including additional automation and management options to further simplify gateway operations at scale.\n\nTo learn more about gateway update options and best practices, explore the documentation: [Update an on-premises data gateway](https://learn.microsoft.com/data-integration/gateway/service-gateway-update?toc=%2Ffabric%2Fdata-factory%2Ftoc.json&amp;bc=fabric%2Fdata-factory%2Fbreadcrumb%2Ftoc.json#update-gateways-from-the-ui-preview).",
  "FeedUrl": "https://blog.fabric.microsoft.com/en-us/blog/feed/",
  "ProcessedDate": "2026-03-18 13:36:37"
}
