{
  "ProcessedDate": "2025-08-15 14:36:07",
  "PubDate": "2025-08-15T11:05:31+00:00",
  "Link": "https://techcommunity.microsoft.com/t5/windows-10/about-the-extendedcoputility-process/m-p/4444150#M17960",
  "FeedUrl": "https://techcommunity.microsoft.com/t5/s/gxcuf89792/rss/Community",
  "Author": "Gordony",
  "FeedName": "Microsoft Tech Community",
  "EnhancedContent": "Every time I start up my computer, it takes up 20-30% of the CPU. I checked the path and found it's in c:/windows/WinS. Does anyone know what this program is? Can I lower the CPU usage a bit?",
  "Title": "About the extendedcoputility process",
  "FeedLevelAuthor": "rss.livelink.threads-in-node",
  "OutputDir": "_community",
  "Description": "Every time I start up my computer, it takes up 20-30% of the CPU. I checked the path and found it's in c:/windows/WinS. Does anyone know what this program is? Can I lower the CPU usage a bit?",
  "Tags": []
}
