{
  "FeedUrl": "https://techcommunity.microsoft.com/t5/s/gxcuf89792/rss/Category?category.id=Azure",
  "FeedLevelAuthor": "rss.livelink.threads-in-node",
  "ProcessedDate": "2025-11-07 19:05:20",
  "Tags": [],
  "Link": "https://techcommunity.microsoft.com/t5/azure-events/build-your-microsoft-ignite-schedule-top-sessions-for-it-pros/ba-p/4468165",
  "Description": "### **Get Ready for Microsoft Ignite**\n\nWelcome back to our Azure Tech Community Microsoft Ignite 2025 series!\n\nIf you joined us for [Your Guide to Azure Community Activations at Microsoft Ignite 2025](https://techcommunity.microsoft.com/blog/azure-events/your-guide-to-azure-community-activations-at-microsoft-ignite-2025/4455501), you already know that Ignite isn’t just about product updates, it’s where ideas, innovation, and community come together.\n\nWith hundreds of sessions across every area of Azure, it can be hard to know where to focus. That’s why we’ve curated a list of sessions tailored specifically for **IT Pros** to help you make the most of your time, strengthen your technical strategy, and get inspired for the year ahead.\n\nUse the Ignite session scheduler feature in the [session catalog](https://ignite.microsoft.com/en-US/sessions) to personalize your agenda, save your favorites, and organize your time at Ignite.\n\n### **Make Every Minute Count: Top Recommended Sessions for IT Pros**\n\nMicrosoft Ignite moves fast, so it pays to plan your path before you arrive.\n\nBy organizing your schedule around your interests and goals, you’ll be able to maximize learning opportunities, connect with peers, and leave with actionable insights.\n\nThe recommendations below highlight our top picks for IT Pros looking to streamline operations, strengthen security, and stay ahead in an evolving cloud landscape.\n\n1. [***End-to-End migration of applications with AI Agents to IaaS and PaaS***](https://ignite.microsoft.com/en-US/sessions/BRK140?source=sessions) *(BRK140*)\nSee how Azure’s new AI-powered migration agents can simplify and accelerate every stage of your migration journey—from assessment to deployment.\n2. [***Architecting for resiliency on Azure Infrastructure***](https://ignite.microsoft.com/en-US/sessions/BRK178?source=sessions) **** *(*BRK178) Discover how to build resilient cloud solutions on Azure by leveraging availability zones, multi-region deployments, and fungible products. This session explores architectural patterns, platform capabilities, and best practices.\n\n1. [***Migrate and Modernize Windows and SQL Server Workloads with Azure***](https://ignite.microsoft.com/en-US/sessions/LAB506-R1?source=sessions) **** *(LAB506-R1)*\nGet hands-on with practical approaches to moving core enterprise workloads to Azure, improving reliability, and optimizing costs.\n2. [***Govern your estate using PowerShell and the CLI with AI***](https://ignite.microsoft.com/en-US/sessions/BRK170?source=sessions) **** (BRK170)\nDiscover how you can use AI for PowerShell and Azure CLI to boost automation and simplify complex commands.\n3. [***Turning Compliance Burden into Competitive Advantage with RegScale***](https://ignite.microsoft.com/en-US/sessions/THR820?source=sessions) (THR820)\nExplore how to use Microsoft’s compliance and governance frameworks to drive efficiency and differentiation.\n\nBefore diving into your targeted sessions, make time for these essential moments that set the stage for everything happening at Ignite.\n\n1. [***Opening Keynote***](https://ignite.microsoft.com/en-US/sessions/KEY01?source=sessions) **** *(KEY01)*\nHear from Microsoft leaders as they unveil the latest innovations shaping the future of AI, cloud, and the developer ecosystem. This is the session that sets the tone for the entire event.\n2. [***Innovation Session: Security in the Agentic Era – the Core Primitive***](https://ignite.microsoft.com/en-US/sessions/BRK1712?source=sessions) ***(****BRK1712)*\nGain a forward-looking perspective on how the rise of Agentic AI will reshape the security landscape for IT operations and enterprise systems.\n3. [**Innovation Session: Scale Smarter: Infrastructure for the Agentic Era**](https://ignite.microsoft.com/en-US/sessions/BRK1704?source=sessions) *(BRK1704)*\nDive into what’s new in Azure Infrastructure—from compute and networking to hybrid management and scalability. Hear from Azure engineering experts on best practices and innovations for modern cloud operations.\n\n### **Plan Smarter with the Session Scheduler**\n\nWith the **“** **add to schedule** **”** **** **feature** in the [session catalog](https://ignite.microsoft.com/en-US/sessions) you’ll be able to:\n\n- Browse and filter all Ignite sessions by topic, product, or persona.\n- Save your favorite sessions to build a personalized schedule.\n- Set reminders and block time for networking, community booths, and demos.\n\n**Stay Connected with the Azure Tech Community**\n\nYour Microsoft Ignite journey doesn’t stop when the sessions end, the conversation continues across the Azure Tech Community.\n\nShare the sessions you’re most excited about using **#MSIgnite** **#AzureTechCommunity**, tag **[azure​](javascript:void%280%29)**, and connect with other IT Pros exploring the future of cloud management and security.\n\nFollow the [Azure Tech Community](https://techcommunity.microsoft.com/category/Azure) for real-time updates, announcements, and product news throughout Ignite.\n\n### **See You at Microsoft Ignite 2025**\n\nWith the right plan in place, every session becomes an opportunity to learn, grow, and connect.\n\nExplore these recommendations, save your favorites, and get ready for an unforgettable [Microsoft Ignite 2025](https://ignite.microsoft.com/en-US/home) experience.",
  "FeedName": "Microsoft Tech Community",
  "PubDate": "2025-11-07T18:46:27+00:00",
  "Title": "Build Your Microsoft Ignite Schedule: Top Sessions for IT Pros",
  "Author": "GalimahB",
  "EnhancedContent": "## Plan your Microsoft Ignite experience around the topics that matter most to you\n\n### **Get Ready for Microsoft Ignite**\n\nWelcome back to our Azure Tech Community Microsoft Ignite 2025 series!\n\nIf you joined us for [Your Guide to Azure Community Activations at Microsoft Ignite 2025](https://techcommunity.microsoft.com/blog/azure-events/your-guide-to-azure-community-activations-at-microsoft-ignite-2025/4455501), you already know that Ignite isn’t just about product updates, it’s where ideas, innovation, and community come together.\n\nWith hundreds of sessions across every area of Azure, it can be hard to know where to focus. That’s why we’ve curated a list of sessions tailored specifically for **IT Pros** to help you make the most of your time, strengthen your technical strategy, and get inspired for the year ahead.\n\nUse the Ignite session scheduler feature in the [session catalog](https://ignite.microsoft.com/en-US/sessions) to personalize your agenda, save your favorites, and organize your time at Ignite.\n\n### **Make Every Minute Count: Top Recommended Sessions for IT Pros**\n\nMicrosoft Ignite moves fast, so it pays to plan your path before you arrive.\n\nBy organizing your schedule around your interests and goals, you’ll be able to maximize learning opportunities, connect with peers, and leave with actionable insights.\n\nThe recommendations below highlight our top picks for IT Pros looking to streamline operations, strengthen security, and stay ahead in an evolving cloud landscape.\n\n1. [***End-to-End migration of applications with AI Agents to IaaS and PaaS***](https://ignite.microsoft.com/en-US/sessions/BRK140?source=sessions) *(BRK140*)\nSee how Azure’s new AI-powered migration agents can simplify and accelerate every stage of your migration journey—from assessment to deployment.\n2. [***Architecting for resiliency on Azure Infrastructure***](https://ignite.microsoft.com/en-US/sessions/BRK178?source=sessions) **** *(*BRK178)                                                                                                                                            Discover how to build resilient cloud solutions on Azure by leveraging availability zones, multi-region deployments, and fungible products. This session explores architectural patterns, platform capabilities, and best practices.\n\n1. [***Migrate and Modernize Windows and SQL Server Workloads with Azure***](https://ignite.microsoft.com/en-US/sessions/LAB506-R1?source=sessions) **** *(LAB506-R1)*\nGet hands-on with practical approaches to moving core enterprise workloads to Azure, improving reliability, and optimizing costs.\n2. [***Govern your estate using PowerShell and the CLI with AI***](https://ignite.microsoft.com/en-US/sessions/BRK170?source=sessions) **** (BRK170)\nDiscover how you can use AI for PowerShell and Azure CLI to boost automation and simplify complex commands.\n3. [***Turning Compliance Burden into Competitive Advantage with RegScale***](https://ignite.microsoft.com/en-US/sessions/THR820?source=sessions) (THR820)\nExplore how to use Microsoft’s compliance and governance frameworks to drive efficiency and differentiation.\n\nBefore diving into your targeted sessions, make time for these essential moments that set the stage for everything happening at Ignite.\n\n1. [***Opening Keynote***](https://ignite.microsoft.com/en-US/sessions/KEY01?source=sessions) **** *(KEY01)*\nHear from Microsoft leaders as they unveil the latest innovations shaping the future of AI, cloud, and the developer ecosystem. This is the session that sets the tone for the entire event.\n2. [***Innovation Session: Security in the Agentic Era – the Core Primitive***](https://ignite.microsoft.com/en-US/sessions/BRK1712?source=sessions) ***(****BRK1712)*\nGain a forward-looking perspective on how the rise of Agentic AI will reshape the security landscape for IT operations and enterprise systems.\n3. [**Innovation Session: Scale Smarter: Infrastructure for the Agentic Era**](https://ignite.microsoft.com/en-US/sessions/BRK1704?source=sessions) *(BRK1704)*\nDive into what’s new in Azure Infrastructure—from compute and networking to hybrid management and scalability. Hear from Azure engineering experts on best practices and innovations for modern cloud operations.\n\n### **Plan Smarter with the Session Scheduler**\n\nWith the **“** **add to schedule** **”** **** **feature** in the [session catalog](https://ignite.microsoft.com/en-US/sessions) you’ll be able to:\n\n- Browse and filter all Ignite sessions by topic, product, or persona.\n- Save your favorite sessions to build a personalized schedule.\n- Set reminders and block time for networking, community booths, and demos.\n\n**Stay Connected with the Azure Tech Community**\n\nYour Microsoft Ignite journey doesn’t stop when the sessions end, the conversation continues across the Azure Tech Community.\n\nShare the sessions you’re most excited about using **#MSIgnite** **#AzureTechCommunity**, tag **[azure​](javascript:void%280%29)**, and connect with other IT Pros exploring the future of cloud management and security.\n\nFollow the [Azure Tech Community](https://techcommunity.microsoft.com/category/Azure) for real-time updates, announcements, and product news throughout Ignite.\n\n### **See You at Microsoft Ignite 2025**\n\nWith the right plan in place, every session becomes an opportunity to learn, grow, and connect.\n\nExplore these recommendations, save your favorites, and get ready for an unforgettable [Microsoft Ignite 2025](https://ignite.microsoft.com/en-US/home) experience.\n\nUpdated Nov 07, 2025\n\nVersion 1.0\n\n[azure](/tag/azure?nodeId=board%3Aazure-events)\n\n[azuretechcommunity](/tag/azuretechcommunity?nodeId=board%3Aazure-events)\n\n[infrastructure (azure)](/tag/infrastructure%20%28azure%29?nodeId=board%3Aazure-events)\n\n[itpros](/tag/itpros?nodeId=board%3Aazure-events)\n\n[msignite](/tag/msignite?nodeId=board%3Aazure-events)\n\n[!\\[GalimahB&#x27;s avatar\\](https://techcommunity.microsoft.com/t5/s/gxcuf89792/m_assets/avatars/default/avatar-1.svg?image-dimensions=50x50)](/users/galimahb/2576822) [GalimahB](/users/galimahb/2576822) ![Icon for Community Manager rank](https://techcommunity.microsoft.com/t5/s/gxcuf89792/images/cmstMi1MV1dRR1U?image-dimensions=100x16&amp;constrain-image=true)Community Manager\n\nJoined July 16, 2024\n\n[View Profile](/users/galimahb/2576822)\n\n/category/azure/blog/azure-events [Azure Events](/category/azure/blog/azure-events) Follow this blog board to get notified when there's new activity",
  "OutputDir": "_community"
}
